pynitrokey/__init__.py
pynitrokey/cli/__init__.py
pynitrokey/cli/exceptions.py
pynitrokey/cli/fido2.py
pynitrokey/cli/monitor.py
pynitrokey/cli/nethsm.py
pynitrokey/cli/nk3/__init__.py
pynitrokey/cli/nk3/pcsc_absent.py
pynitrokey/cli/nk3/piv.py
pynitrokey/cli/nk3/secrets.py
pynitrokey/cli/nk3/update.py
pynitrokey/cli/nkfido2.py
pynitrokey/cli/nkpk.py
pynitrokey/cli/pro.py
pynitrokey/cli/program.py
pynitrokey/cli/start.py
pynitrokey/cli/storage.py
pynitrokey/cli/trussed/__init__.py
pynitrokey/cli/trussed/test.py
pynitrokey/cli/trussed/tests.py
pynitrokey/cli/update.py
pynitrokey/confconsts.py
pynitrokey/conftest.py
pynitrokey/exceptions.py
pynitrokey/fido2/__init__.py
pynitrokey/fido2/client.py
pynitrokey/fido2/commands.py
pynitrokey/helpers.py
pynitrokey/libnk.py
pynitrokey/nk3/piv_app.py
pynitrokey/nk_headers/NK_C_API__3.4.0.h
pynitrokey/nk_headers/NK_C_API__3.4.1.h
pynitrokey/nk_headers/NK_C_API__3.5.0.h
pynitrokey/nk_headers/NK_C_API__3.6.0.h
pynitrokey/py.typed
pynitrokey/start/__init__.py
pynitrokey/start/gnuk_token.py
pynitrokey/start/kdf_calc.py
pynitrokey/start/rsa.py
pynitrokey/start/rsa_pub_key.py
pynitrokey/start/threaded_log.py
pynitrokey/start/upgrade_by_passwd.py
pynitrokey/start/usb_strings.py
pynitrokey/test_secrets_app.py
pynitrokey/tlv.py
pynitrokey-0.11.2.dist-info/METADATA
pynitrokey-0.11.2.dist-info/WHEEL
pynitrokey-0.11.2.dist-info/entry_points.txt
pynitrokey-0.11.2.dist-info/licenses/LICENSES/Apache-2.0.txt
pynitrokey-0.11.2.dist-info/licenses/LICENSES/GPL-3.0-or-later.txt
pynitrokey-0.11.2.dist-info/licenses/LICENSES/LGPL-3.0-only.txt
pynitrokey-0.11.2.dist-info/licenses/LICENSES/MIT.txt
pynitrokey-0.11.2.dist-info/RECORD
