Metadata-Version: 2.4
Name: pynitrokey
Version: 0.11.2
Summary: Python client for Nitrokey devices
License: Apache-2.0 OR MIT
License-File: LICENSES/Apache-2.0.txt
License-File: LICENSES/GPL-3.0-or-later.txt
License-File: LICENSES/LGPL-3.0-only.txt
License-File: LICENSES/MIT.txt
Author: Nitrokey
Author-email: pypi@nitrokey.com
Requires-Python: >=3.10
Classifier: Intended Audience :: Developers
Classifier: Intended Audience :: End Users/Desktop
Classifier: License :: Other/Proprietary License
Classifier: Programming Language :: Python :: 3
Classifier: Programming Language :: Python :: 3.10
Classifier: Programming Language :: Python :: 3.11
Classifier: Programming Language :: Python :: 3.12
Classifier: Programming Language :: Python :: 3.13
Provides-Extra: pcsc
Requires-Dist: cffi (>=1.15,<3)
Requires-Dist: click (>=8.2,<9)
Requires-Dist: cryptography (>=43,<47)
Requires-Dist: fido2 (>=2,<3)
Requires-Dist: hidapi (>=0.14,<0.15)
Requires-Dist: hidapi (>=0.14.0.post1,<0.14.0.post4) ; sys_platform == "linux"
Requires-Dist: intelhex (>=2.3,<3)
Requires-Dist: libusb1 (>=3,<4)
Requires-Dist: nethsm (>=2.0.1,<3)
Requires-Dist: nitrokey (>=0.4,<0.5)
Requires-Dist: nkdfu (>=0.2,<0.3)
Requires-Dist: pyscard (>=2,<3) ; extra == "pcsc"
Requires-Dist: pyserial (>=3.5,<4)
Requires-Dist: pyusb (>=1.2,<2)
Requires-Dist: requests (>=2.16,<3)
Requires-Dist: semver (>=3,<4)
Requires-Dist: tlv8 (>=0.10,<0.11)
Requires-Dist: tqdm (>=4.64,<5)
Project-URL: Repository, https://github.com/Nitrokey/pynitrokey
